{
	"animations": [
		{
			"loop": false,
			"offsets": [
				0,
				0
			],
			"anim": "idle",
			"fps": 24,
			"name": "GoldHead Idle",
			"indices": []
		},
		{
			"loop": false,
			"offsets": [
				276,
				22
			],
			"anim": "singLEFT",
			"fps": 24,
			"name": "GoldHead Left Full",
			"indices": []
		},
		{
			"loop": false,
			"offsets": [
				50,
				-180
			],
			"anim": "singDOWN",
			"fps": 24,
			"name": "GoldHead DOwn full",
			"indices": []
		},
		{
			"loop": false,
			"offsets": [
				-103,
				80
			],
			"anim": "singRIGHT",
			"fps": 24,
			"name": "GoldHead Right",
			"indices": []
		},
		{
			"loop": false,
			"offsets": [
				0,
				207
			],
			"anim": "singUP",
			"fps": 24,
			"name": "GoldHead Up",
			"indices": []
		}
	],
	"no_antialiasing": false,
	"image": "characters/Gold/GoldHead Sheet",
	"position": [
		-25,
		600
	],
	"healthicon": "face",
	"flip_x": false,
	"healthbar_colors": [
		255,
		255,
		255
	],
	"camera_position": [
		0,
		-500
	],
	"sing_duration": 6.1,
	"scale": 1.3
}