{
	"animations": [
		{
			"offsets": [
				0,
				0
			],
			"loop": false,
			"fps": 24,
			"anim": "singLEFT",
			"indices": [],
			"name": "coral left"
		},
		{
			"offsets": [
				0,
				0
			],
			"loop": false,
			"fps": 24,
			"anim": "singDOWN",
			"indices": [],
			"name": "coral down"
		},
		{
			"offsets": [
				0,
				0
			],
			"loop": false,
			"fps": 24,
			"anim": "singUP",
			"indices": [],
			"name": "coral up"
		},
		{
			"offsets": [
				0,
				0
			],
			"loop": false,
			"fps": 24,
			"anim": "singRIGHT",
			"indices": [],
			"name": "coral right"
		},
		{
			"offsets": [
				0,
				0
			],
			"loop": false,
			"fps": 24,
			"anim": "idle",
			"indices": [],
			"name": "coral idle"
		}
	],
	"no_antialiasing": false,
	"image": "characters/coral",
	"position": [
		-450,
		100
	],
	"healthicon": "coralreal",
	"flip_x": true,
	"healthbar_colors": [
		255,
		78,
		134
	],
	"camera_position": [
		210,
		-50
	],
	"sing_duration": 6.1,
	"scale": 1.3
}