{
	"song": {
		"player1": "bf",
		"gfVersion": "gf-position",
		"notes": [
			{
				"sectionNotes": [
					[
						0,
						1,
						0
					],
					[
						230.769230769231,
						1,
						0
					],
					[
						1384.61538461538,
						1,
						0
					],
					[
						461.538461538462,
						2,
						800
					],
					[
						1615.38461538462,
						1,
						0
					]
				],
				"typeOfSection": 0,
				"lengthInSteps": 16,
				"gfSection": false,
				"altAnim": false,
				"mustHitSection": true,
				"changeBPM": false,
				"bpm": 150
			},
			{
				"sectionNotes": [
					[
						1846.15384615385,
						2,
						800
					],
					[
						2769.23076923077,
						1,
						0
					],
					[
						3000,
						0,
						0
					],
					[
						3230.76923076923,
						2,
						350
					]
				],
				"typeOfSection": 0,
				"lengthInSteps": 16,
				"gfSection": false,
				"altAnim": false,
				"mustHitSection": true,
				"changeBPM": false,
				"bpm": 150
			},
			{
				"sectionNotes": [
					[
						3692.30769230769,
						3,
						350
					],
					[
						4153.84615384615,
						0,
						350
					],
					[
						4615.38461538462,
						0,
						350
					],
					[
						5076.92307692308,
						3,
						350
					]
				],
				"typeOfSection": 0,
				"lengthInSteps": 16,
				"gfSection": false,
				"altAnim": false,
				"mustHitSection": true,
				"changeBPM": false,
				"bpm": 130
			},
			{
				"sectionNotes": [
					[
						5538.46153846154,
						1,
						0
					],
					[
						5769.23076923077,
						0,
						0
					],
					[
						6000,
						3,
						800
					],
					[
						6923.07692307692,
						1,
						0
					],
					[
						7153.84615384615,
						0,
						0
					]
				],
				"typeOfSection": 0,
				"lengthInSteps": 16,
				"gfSection": false,
				"altAnim": false,
				"mustHitSection": true,
				"changeBPM": false,
				"bpm": 130
			},
			{
				"sectionNotes": [
					[
						7384.61538461538,
						3,
						800
					],
					[
						8307.69230769231,
						1,
						0
					],
					[
						8538.46153846154,
						0,
						0
					],
					[
						8769.23076923077,
						2,
						0
					],
					[
						9000,
						3,
						0
					]
				],
				"typeOfSection": 0,
				"lengthInSteps": 16,
				"gfSection": false,
				"altAnim": false,
				"mustHitSection": true,
				"changeBPM": false,
				"bpm": 130
			},
			{
				"sectionNotes": [
					[
						9230.76923076923,
						1,
						350
					],
					[
						9692.30769230769,
						3,
						350
					],
					[
						10153.8461538462,
						2,
						800
					]
				],
				"typeOfSection": 0,
				"lengthInSteps": 16,
				"gfSection": false,
				"altAnim": false,
				"mustHitSection": true,
				"changeBPM": false,
				"bpm": 130
			},
			{
				"sectionNotes": [
					[
						11076.9230769231,
						3,
						0
					],
					[
						11307.6923076923,
						3,
						0
					],
					[
						11538.4615384615,
						2,
						800
					],
					[
						12461.5384615385,
						0,
						0
					],
					[
						12692.3076923077,
						1,
						0
					]
				],
				"typeOfSection": 0,
				"lengthInSteps": 16,
				"gfSection": false,
				"altAnim": false,
				"mustHitSection": true,
				"changeBPM": false,
				"bpm": 130
			},
			{
				"sectionNotes": [
					[
						12923.0769230769,
						3,
						800
					],
					[
						13846.1538461538,
						0,
						0
					],
					[
						14076.9230769231,
						1,
						0
					],
					[
						14307.6923076923,
						0,
						350
					]
				],
				"typeOfSection": 0,
				"lengthInSteps": 16,
				"gfSection": false,
				"altAnim": false,
				"mustHitSection": true,
				"changeBPM": false,
				"bpm": 130
			},
			{
				"sectionNotes": [
					[
						14769.2307692308,
						3,
						350
					],
					[
						15230.7692307692,
						2,
						350
					],
					[
						15692.3076923077,
						3,
						800
					]
				],
				"typeOfSection": 0,
				"lengthInSteps": 16,
				"gfSection": false,
				"altAnim": false,
				"mustHitSection": true,
				"changeBPM": false,
				"bpm": 130
			},
			{
				"sectionNotes": [
					[
						16615.3846153846,
						3,
						0
					],
					[
						16846.1538461538,
						3,
						0
					],
					[
						17076.9230769231,
						2,
						800
					],
					[
						18000,
						0,
						0
					],
					[
						18230.7692307692,
						1,
						0
					]
				],
				"typeOfSection": 0,
				"lengthInSteps": 16,
				"gfSection": false,
				"altAnim": false,
				"mustHitSection": true,
				"changeBPM": false,
				"bpm": 130
			},
			{
				"sectionNotes": [
					[
						18461.5384615385,
						3,
						800
					],
					[
						19384.6153846154,
						0,
						0
					],
					[
						19615.3846153846,
						1,
						0
					],
					[
						19846.1538461538,
						0,
						350
					]
				],
				"typeOfSection": 0,
				"lengthInSteps": 16,
				"gfSection": false,
				"altAnim": false,
				"mustHitSection": true,
				"changeBPM": false,
				"bpm": 130
			},
			{
				"sectionNotes": [
					[
						20307.6923076923,
						1,
						350
					],
					[
						20769.2307692308,
						3,
						350
					],
					[
						21230.7692307692,
						0,
						800
					]
				],
				"typeOfSection": 0,
				"lengthInSteps": 16,
				"gfSection": false,
				"altAnim": false,
				"mustHitSection": true,
				"changeBPM": false,
				"bpm": 130
			},
			{
				"sectionNotes": [],
				"typeOfSection": 0,
				"lengthInSteps": 16,
				"gfSection": false,
				"altAnim": false,
				"mustHitSection": true,
				"changeBPM": false,
				"bpm": 130
			},
			{
				"sectionNotes": [
					[
						24923.0769230769,
						1,
						0
					],
					[
						25153.8461538462,
						3,
						0
					],
					[
						25384.6153846154,
						2,
						350
					]
				],
				"typeOfSection": 0,
				"lengthInSteps": 16,
				"gfSection": false,
				"altAnim": false,
				"mustHitSection": false,
				"changeBPM": false,
				"bpm": 130
			},
			{
				"sectionNotes": [
					[
						26307.6923076923,
						3,
						350
					],
					[
						27230.7692307692,
						1,
						350
					]
				],
				"typeOfSection": 0,
				"lengthInSteps": 16,
				"gfSection": false,
				"altAnim": false,
				"mustHitSection": false,
				"changeBPM": false,
				"bpm": 130
			},
			{
				"sectionNotes": [
					[
						27692.3076923077,
						3,
						0
					],
					[
						27923.0769230769,
						1,
						0
					],
					[
						28153.8461538462,
						0,
						800
					]
				],
				"typeOfSection": 0,
				"lengthInSteps": 16,
				"gfSection": false,
				"altAnim": false,
				"mustHitSection": false,
				"changeBPM": false,
				"bpm": 130
			},
			{
				"sectionNotes": [
					[
						30461.5384615385,
						1,
						0
					],
					[
						30923.0769230769,
						2,
						0
					],
					[
						31153.8461538462,
						3,
						0
					]
				],
				"typeOfSection": 0,
				"lengthInSteps": 16,
				"gfSection": false,
				"altAnim": false,
				"mustHitSection": false,
				"changeBPM": false,
				"bpm": 130
			},
			{
				"sectionNotes": [
					[
						31846.1538461539,
						0,
						350
					],
					[
						32307.6923076923,
						2,
						800
					]
				],
				"typeOfSection": 0,
				"lengthInSteps": 16,
				"gfSection": false,
				"altAnim": false,
				"mustHitSection": false,
				"changeBPM": false,
				"bpm": 130
			},
			{
				"sectionNotes": [
					[
						33230.7692307692,
						1,
						0
					],
					[
						33461.5384615385,
						1,
						0
					],
					[
						33692.3076923077,
						2,
						800
					]
				],
				"typeOfSection": 0,
				"lengthInSteps": 16,
				"gfSection": false,
				"altAnim": false,
				"mustHitSection": false,
				"changeBPM": false,
				"bpm": 130
			},
			{
				"sectionNotes": [
					[
						35076.9230769231,
						0,
						800
					],
					[
						36000,
						3,
						0
					],
					[
						36230.7692307692,
						1,
						0
					]
				],
				"typeOfSection": 0,
				"lengthInSteps": 16,
				"gfSection": false,
				"altAnim": false,
				"mustHitSection": false,
				"changeBPM": false,
				"bpm": 130
			},
			{
				"sectionNotes": [
					[
						37384.6153846154,
						2,
						350
					],
					[
						37846.1538461539,
						3,
						800
					]
				],
				"typeOfSection": 0,
				"lengthInSteps": 16,
				"gfSection": false,
				"altAnim": false,
				"mustHitSection": false,
				"changeBPM": false,
				"bpm": 130
			},
			{
				"sectionNotes": [
					[
						38769.2307692308,
						1,
						0
					],
					[
						39000,
						1,
						0
					]
				],
				"typeOfSection": 0,
				"lengthInSteps": 16,
				"gfSection": false,
				"altAnim": false,
				"mustHitSection": false,
				"changeBPM": false,
				"bpm": 130
			},
			{
				"sectionNotes": [
					[
						41538.4615384615,
						0,
						0
					],
					[
						41769.2307692308,
						1,
						0
					],
					[
						42000,
						2,
						350
					]
				],
				"typeOfSection": 0,
				"lengthInSteps": 16,
				"gfSection": false,
				"altAnim": false,
				"mustHitSection": false,
				"changeBPM": false,
				"bpm": 130
			},
			{
				"sectionNotes": [
					[
						42461.5384615385,
						3,
						800
					],
					[
						43384.6153846154,
						0,
						1600
					]
				],
				"typeOfSection": 0,
				"lengthInSteps": 16,
				"gfSection": false,
				"altAnim": false,
				"mustHitSection": false,
				"changeBPM": false,
				"bpm": 130
			},
			{
				"sectionNotes": [
					[
						45230.7692307692,
						1,
						2000
					]
				],
				"typeOfSection": 0,
				"lengthInSteps": 16,
				"gfSection": false,
				"altAnim": false,
				"mustHitSection": false,
				"changeBPM": false,
				"bpm": 130
			},
			{
				"sectionNotes": [],
				"typeOfSection": 0,
				"lengthInSteps": 16,
				"gfSection": false,
				"altAnim": false,
				"mustHitSection": true,
				"changeBPM": false,
				"bpm": 130
			},
			{
				"sectionNotes": [
					[
						48000,
						3,
						0,
						"Alt Animation"
					],
					[
						48230.7692307692,
						3,
						0,
						"Alt Animation"
					],
					[
						48115.3846153846,
						3,
						0,
						"Alt Animation"
					],
					[
						48346.1538461538,
						3,
						0,
						"Alt Animation"
					],
					[
						48461.5384615385,
						1,
						0,
						"Alt Animation"
					],
					[
						48576.9230769231,
						1,
						0,
						"Alt Animation"
					],
					[
						48692.3076923077,
						1,
						0,
						"Alt Animation"
					],
					[
						48807.6923076923,
						1,
						0,
						"Alt Animation"
					]
				],
				"typeOfSection": 0,
				"lengthInSteps": 16,
				"gfSection": false,
				"altAnim": false,
				"mustHitSection": false,
				"changeBPM": false,
				"bpm": 130
			},
			{
				"sectionNotes": [],
				"typeOfSection": 0,
				"lengthInSteps": 16,
				"gfSection": false,
				"altAnim": false,
				"mustHitSection": true,
				"changeBPM": false,
				"bpm": 130
			},
			{
				"sectionNotes": [
					[
						51692.3076923077,
						0,
						0
					]
				],
				"typeOfSection": 0,
				"lengthInSteps": 16,
				"gfSection": false,
				"altAnim": false,
				"mustHitSection": true,
				"changeBPM": false,
				"bpm": 130
			},
			{
				"sectionNotes": [
					[
						53538.4615384615,
						0,
						0
					],
					[
						53599.0384615384,
						1,
						0
					],
					[
						53653.8461538461,
						3,
						0
					],
					[
						53708.6538461538,
						2,
						0
					],
					[
						53769.2307692308,
						0,
						0
					],
					[
						53821.1538461538,
						3,
						0
					],
					[
						53884.6153846154,
						2,
						0
					],
					[
						53948.0769230769,
						1,
						0
					],
					[
						54000,
						3,
						0
					],
					[
						54043.2692307692,
						0,
						0
					],
					[
						54115.3846153846,
						2,
						0
					],
					[
						54181.7307692308,
						3,
						0
					],
					[
						54230.7692307692,
						1,
						0
					],
					[
						54282.6923076923,
						0,
						0
					],
					[
						54346.1538461538,
						2,
						0
					],
					[
						54400.9615384615,
						1,
						0
					],
					[
						54461.5384615384,
						3,
						0
					],
					[
						54510.5769230769,
						2,
						0
					],
					[
						54576.9230769231,
						1,
						0
					],
					[
						54631.7307692308,
						2,
						0
					],
					[
						54692.3076923077,
						3,
						0
					],
					[
						54747.1153846154,
						0,
						0
					],
					[
						54807.6923076923,
						1,
						0
					],
					[
						54923.0769230769,
						1,
						0
					],
					[
						54859.6153846154,
						2,
						0
					],
					[
						54972.1153846154,
						0,
						0
					],
					[
						55038.4615384615,
						3,
						0
					],
					[
						55093.2692307692,
						2,
						0
					],
					[
						55153.8461538461,
						1,
						0
					],
					[
						55205.7692307692,
						0,
						0
					],
					[
						55269.2307692308,
						1,
						0
					]
				],
				"typeOfSection": 0,
				"lengthInSteps": 16,
				"gfSection": false,
				"altAnim": false,
				"mustHitSection": true,
				"changeBPM": false,
				"bpm": 130
			},
			{
				"lengthInSteps": 16,
				"typeOfSection": 0,
				"sectionNotes": [
					[
						55384.6153846154,
						1,
						0
					],
					[
						55615.3846153846,
						3,
						0
					],
					[
						55846.1538461538,
						2,
						0
					],
					[
						56076.9230769231,
						3,
						0
					],
					[
						56307.6923076923,
						1,
						0
					],
					[
						56538.4615384615,
						3,
						0
					],
					[
						56769.2307692308,
						2,
						0
					],
					[
						57000,
						2,
						0
					],
					[
						57115.3846153846,
						2,
						0
					]
				],
				"altAnim": false,
				"gfSection": false,
				"bpm": 130,
				"changeBPM": false,
				"mustHitSection": false
			},
			{
				"sectionNotes": [
					[
						57230.7692307692,
						1,
						0
					],
					[
						57461.5384615384,
						3,
						0
					],
					[
						57692.3076923077,
						2,
						0
					],
					[
						57923.0769230769,
						3,
						0
					],
					[
						58384.6153846154,
						3,
						0
					],
					[
						58615.3846153846,
						2,
						0
					],
					[
						58846.1538461538,
						2,
						0
					],
					[
						58961.5384615384,
						2,
						0
					],
					[
						58153.8461538461,
						0,
						0,
						"shoot"
					],
					[
						58153.8461538461,
						1,
						0,
						"shoot"
					],
					[
						58153.8461538461,
						2,
						0,
						"shoot"
					],
					[
						58153.8461538461,
						3,
						0,
						"shoot"
					]
				],
				"typeOfSection": 0,
				"lengthInSteps": 16,
				"gfSection": false,
				"altAnim": false,
				"mustHitSection": true,
				"changeBPM": false,
				"bpm": 130
			},
			{
				"sectionNotes": [
					[
						59076.9230769231,
						2,
						0
					],
					[
						59192.3076923077,
						3,
						0
					],
					[
						59307.6923076923,
						1,
						0
					],
					[
						59423.0769230769,
						3,
						0
					],
					[
						59538.4615384615,
						2,
						0
					],
					[
						59653.8461538461,
						3,
						0
					],
					[
						59769.2307692308,
						0,
						0
					],
					[
						59884.6153846154,
						1,
						0
					],
					[
						60000,
						2,
						0
					],
					[
						60115.3846153846,
						3,
						0
					],
					[
						60230.7692307692,
						1,
						0
					],
					[
						60346.1538461538,
						3,
						0
					],
					[
						60461.5384615384,
						2,
						0
					],
					[
						60576.9230769231,
						3,
						0
					],
					[
						60692.3076923077,
						1,
						0
					],
					[
						60807.6923076923,
						2,
						0
					]
				],
				"typeOfSection": 0,
				"lengthInSteps": 16,
				"gfSection": false,
				"altAnim": false,
				"mustHitSection": false,
				"changeBPM": false,
				"bpm": 130
			},
			{
				"typeOfSection": 0,
				"sectionNotes": [
					[
						60923.0769230769,
						2,
						0
					],
					[
						61038.4615384615,
						3,
						0
					],
					[
						61153.8461538461,
						1,
						0
					],
					[
						61269.2307692307,
						3,
						0
					],
					[
						61384.6153846154,
						2,
						0
					],
					[
						61500,
						3,
						0
					],
					[
						61615.3846153846,
						0,
						0
					],
					[
						61730.7692307692,
						1,
						0
					],
					[
						61846.1538461538,
						2,
						0
					],
					[
						61961.5384615384,
						3,
						0
					],
					[
						62076.9230769231,
						1,
						0
					],
					[
						62192.3076923077,
						3,
						0
					],
					[
						62307.6923076923,
						2,
						0
					],
					[
						62423.0769230769,
						3,
						0
					],
					[
						62538.4615384615,
						1,
						0
					],
					[
						62653.8461538461,
						2,
						0
					]
				],
				"sectionBeats": 4,
				"altAnim": false,
				"gfSection": false,
				"bpm": 130,
				"changeBPM": false,
				"mustHitSection": true
			},
			{
				"typeOfSection": 0,
				"sectionNotes": [
					[
						62769.2307692307,
						3,
						0
					],
					[
						62884.6153846154,
						1,
						0
					],
					[
						63000,
						3,
						0
					],
					[
						63115.3846153846,
						1,
						0
					],
					[
						63230.7692307692,
						3,
						0
					],
					[
						63346.1538461538,
						1,
						0
					],
					[
						63461.5384615384,
						3,
						0
					],
					[
						63576.923076923,
						1,
						0
					],
					[
						62829.8076923077,
						2,
						0
					],
					[
						63057.6923076923,
						2,
						0
					],
					[
						63282.6923076923,
						2,
						0
					],
					[
						63519.2307692307,
						2,
						0
					],
					[
						62939.423076923,
						0,
						0
					],
					[
						63167.3076923077,
						0,
						0
					],
					[
						63398.0769230769,
						0,
						0
					],
					[
						63625.9615384615,
						0,
						0
					],
					[
						63692.3076923077,
						3,
						0
					],
					[
						63923.0769230769,
						1,
						0
					],
					[
						64153.8461538461,
						3,
						0
					],
					[
						64384.6153846154,
						1,
						0
					]
				],
				"sectionBeats": 4,
				"altAnim": false,
				"gfSection": false,
				"bpm": 130,
				"changeBPM": false,
				"mustHitSection": false
			},
			{
				"typeOfSection": 0,
				"sectionNotes": [
					[
						64615.3846153846,
						3,
						0
					],
					[
						64730.7692307692,
						1,
						0
					],
					[
						64846.1538461538,
						3,
						0
					],
					[
						64961.5384615384,
						1,
						0
					],
					[
						65076.923076923,
						3,
						0
					],
					[
						65192.3076923077,
						1,
						0
					],
					[
						65307.6923076923,
						3,
						0
					],
					[
						65423.0769230769,
						1,
						0
					],
					[
						64675.9615384615,
						2,
						0
					],
					[
						64903.8461538461,
						2,
						0
					],
					[
						65128.8461538461,
						2,
						0
					],
					[
						65365.3846153846,
						2,
						0
					],
					[
						64785.5769230769,
						0,
						0
					],
					[
						65013.4615384615,
						0,
						0
					],
					[
						65244.2307692307,
						0,
						0
					],
					[
						65472.1153846154,
						0,
						0
					],
					[
						65538.4615384615,
						2,
						0
					],
					[
						66000,
						2,
						0
					],
					[
						65769.2307692307,
						0,
						0
					],
					[
						66230.7692307692,
						1,
						0
					]
				],
				"sectionBeats": 4,
				"altAnim": false,
				"gfSection": false,
				"bpm": 130,
				"changeBPM": false,
				"mustHitSection": false
			},
			{
				"typeOfSection": 0,
				"sectionNotes": [
					[
						66461.5384615384,
						3,
						0
					],
					[
						66576.923076923,
						1,
						0
					],
					[
						66692.3076923077,
						3,
						0
					],
					[
						66807.6923076923,
						1,
						0
					],
					[
						66923.0769230769,
						3,
						0
					],
					[
						67038.4615384615,
						1,
						0
					],
					[
						67153.8461538461,
						3,
						0
					],
					[
						67269.2307692307,
						1,
						0
					],
					[
						66522.1153846154,
						2,
						0
					],
					[
						66750,
						2,
						0
					],
					[
						66975,
						2,
						0
					],
					[
						67211.5384615384,
						2,
						0
					],
					[
						66631.7307692307,
						0,
						0
					],
					[
						66859.6153846154,
						0,
						0
					],
					[
						67090.3846153846,
						0,
						0
					],
					[
						67318.2692307692,
						0,
						0
					],
					[
						67384.6153846154,
						3,
						0
					],
					[
						67615.3846153846,
						1,
						0
					],
					[
						68076.923076923,
						1,
						0
					],
					[
						67846.1538461538,
						3,
						0,
						"shoot"
					],
					[
						67846.1538461538,
						2,
						0,
						"shoot"
					],
					[
						67846.1538461538,
						1,
						0,
						"shoot"
					],
					[
						67846.1538461538,
						0,
						0,
						"shoot"
					]
				],
				"sectionBeats": 4,
				"altAnim": false,
				"gfSection": false,
				"bpm": 130,
				"changeBPM": false,
				"mustHitSection": true
			},
			{
				"typeOfSection": 0,
				"sectionNotes": [
					[
						68307.6923076923,
						3,
						0
					],
					[
						68423.0769230769,
						1,
						0
					],
					[
						68538.4615384615,
						3,
						0
					],
					[
						68653.8461538461,
						1,
						0
					],
					[
						68769.2307692307,
						3,
						0
					],
					[
						68884.6153846154,
						1,
						0
					],
					[
						69000,
						3,
						0
					],
					[
						69115.3846153846,
						1,
						0
					],
					[
						68368.2692307692,
						2,
						0
					],
					[
						68596.1538461538,
						2,
						0
					],
					[
						68821.1538461538,
						2,
						0
					],
					[
						69057.6923076923,
						2,
						0
					],
					[
						68477.8846153846,
						0,
						0
					],
					[
						68705.7692307692,
						0,
						0
					],
					[
						68936.5384615384,
						0,
						0
					],
					[
						69164.423076923,
						0,
						0
					],
					[
						69230.7692307692,
						2,
						0
					],
					[
						69461.5384615384,
						0,
						0
					],
					[
						69923.0769230769,
						1,
						0
					],
					[
						69692.3076923077,
						2,
						0,
						"shoot"
					],
					[
						69692.3076923077,
						0,
						0,
						"shoot"
					],
					[
						69692.3076923077,
						1,
						0,
						"shoot"
					],
					[
						69692.3076923077,
						3,
						0,
						"shoot"
					]
				],
				"sectionBeats": 4,
				"altAnim": false,
				"gfSection": false,
				"bpm": 130,
				"changeBPM": false,
				"mustHitSection": true
			},
			{
				"typeOfSection": 0,
				"sectionNotes": [
					[
						70153.8461538461,
						2,
						0
					],
					[
						70269.2307692308,
						3,
						0
					],
					[
						70384.6153846154,
						1,
						0
					],
					[
						70500,
						3,
						0
					],
					[
						70615.3846153846,
						2,
						0
					],
					[
						70730.7692307692,
						3,
						0
					],
					[
						70846.1538461538,
						0,
						0
					],
					[
						70961.5384615384,
						1,
						0
					],
					[
						71076.923076923,
						2,
						0
					],
					[
						71192.3076923077,
						3,
						0
					],
					[
						71307.6923076923,
						1,
						0
					],
					[
						71423.0769230769,
						3,
						0
					],
					[
						71538.4615384615,
						2,
						0
					],
					[
						71653.8461538461,
						3,
						0
					],
					[
						71769.2307692308,
						1,
						0
					],
					[
						71884.6153846154,
						2,
						0
					]
				],
				"sectionBeats": 4,
				"altAnim": false,
				"gfSection": false,
				"bpm": 130,
				"changeBPM": false,
				"mustHitSection": false
			},
			{
				"typeOfSection": 0,
				"sectionNotes": [
					[
						72000,
						2,
						0
					],
					[
						72115.3846153846,
						3,
						0
					],
					[
						72230.7692307692,
						1,
						0
					],
					[
						72346.1538461538,
						3,
						0
					],
					[
						72461.5384615384,
						2,
						0
					],
					[
						72576.9230769231,
						3,
						0
					],
					[
						72692.3076923077,
						0,
						0
					],
					[
						72807.6923076923,
						1,
						0
					],
					[
						72923.0769230769,
						2,
						0
					],
					[
						73038.4615384615,
						3,
						0
					],
					[
						73153.8461538461,
						1,
						0
					],
					[
						73269.2307692308,
						3,
						0
					],
					[
						73384.6153846154,
						2,
						0
					],
					[
						73500,
						3,
						0
					],
					[
						73615.3846153846,
						1,
						0
					],
					[
						73730.7692307692,
						2,
						0
					]
				],
				"sectionBeats": 4,
				"altAnim": false,
				"gfSection": false,
				"bpm": 130,
				"changeBPM": false,
				"mustHitSection": false
			},
			{
				"typeOfSection": 0,
				"sectionNotes": [
					[
						73846.1538461538,
						3,
						0
					],
					[
						73961.5384615384,
						1,
						0
					],
					[
						74076.9230769231,
						3,
						0
					],
					[
						74192.3076923077,
						1,
						0
					],
					[
						74307.6923076923,
						3,
						0
					],
					[
						74423.0769230769,
						1,
						0
					],
					[
						74538.4615384615,
						3,
						0
					],
					[
						74653.8461538461,
						1,
						0
					],
					[
						73906.7307692308,
						2,
						0
					],
					[
						74134.6153846154,
						2,
						0
					],
					[
						74359.6153846154,
						2,
						0
					],
					[
						74596.1538461538,
						2,
						0
					],
					[
						74016.3461538461,
						0,
						0
					],
					[
						74244.2307692308,
						0,
						0
					],
					[
						74475,
						0,
						0
					],
					[
						74702.8846153846,
						0,
						0
					],
					[
						74769.2307692308,
						3,
						0
					],
					[
						75000,
						1,
						0
					],
					[
						75230.7692307692,
						3,
						0
					],
					[
						75461.5384615384,
						1,
						0
					]
				],
				"sectionBeats": 4,
				"altAnim": false,
				"gfSection": false,
				"bpm": 130,
				"changeBPM": false,
				"mustHitSection": false
			},
			{
				"typeOfSection": 0,
				"sectionNotes": [
					[
						75692.3076923077,
						3,
						0
					],
					[
						75807.6923076923,
						1,
						0
					],
					[
						75923.0769230769,
						3,
						0
					],
					[
						76038.4615384615,
						1,
						0
					],
					[
						76153.8461538461,
						3,
						0
					],
					[
						76269.2307692308,
						1,
						0
					],
					[
						76384.6153846154,
						3,
						0
					],
					[
						76500,
						1,
						0
					],
					[
						75752.8846153846,
						2,
						0
					],
					[
						75980.7692307692,
						2,
						0
					],
					[
						76205.7692307692,
						2,
						0
					],
					[
						76442.3076923077,
						2,
						0
					],
					[
						75862.5,
						0,
						0
					],
					[
						76090.3846153846,
						0,
						0
					],
					[
						76321.1538461538,
						0,
						0
					],
					[
						76549.0384615384,
						0,
						0
					],
					[
						76615.3846153846,
						2,
						0
					],
					[
						77076.923076923,
						2,
						0
					],
					[
						76846.1538461538,
						0,
						0
					],
					[
						77307.6923076923,
						1,
						0
					]
				],
				"sectionBeats": 4,
				"altAnim": false,
				"gfSection": false,
				"bpm": 130,
				"changeBPM": false,
				"mustHitSection": false
			},
			{
				"typeOfSection": 0,
				"sectionNotes": [
					[
						77538.4615384615,
						2,
						0
					],
					[
						77653.8461538461,
						3,
						0
					],
					[
						77884.6153846153,
						3,
						0
					],
					[
						78000,
						2,
						0
					],
					[
						78115.3846153846,
						3,
						0
					],
					[
						78230.7692307692,
						0,
						0
					],
					[
						78346.1538461538,
						1,
						0
					],
					[
						78461.5384615384,
						2,
						0
					],
					[
						78576.9230769231,
						3,
						0
					],
					[
						78807.6923076923,
						3,
						0
					],
					[
						79038.4615384615,
						3,
						0
					],
					[
						79153.8461538461,
						1,
						0
					],
					[
						79269.2307692308,
						2,
						0
					],
					[
						77769.2307692307,
						0,
						0,
						"shoot"
					],
					[
						77769.2307692307,
						1,
						0,
						"shoot"
					],
					[
						78692.3076923077,
						1,
						0,
						"shoot"
					],
					[
						78692.3076923077,
						0,
						0,
						"shoot"
					],
					[
						78923.0769230769,
						1,
						0,
						"shoot"
					],
					[
						78923.0769230769,
						2,
						0,
						"shoot"
					]
				],
				"sectionBeats": 4,
				"altAnim": false,
				"gfSection": false,
				"bpm": 130,
				"changeBPM": false,
				"mustHitSection": true
			},
			{
				"typeOfSection": 0,
				"sectionNotes": [
					[
						79384.6153846153,
						2,
						0
					],
					[
						79500,
						3,
						0
					],
					[
						79615.3846153846,
						1,
						0
					],
					[
						79730.7692307692,
						3,
						0
					],
					[
						79846.1538461538,
						2,
						0
					],
					[
						79961.5384615384,
						3,
						0
					],
					[
						80076.9230769231,
						0,
						0
					],
					[
						80192.3076923077,
						1,
						0
					],
					[
						80307.6923076923,
						2,
						0
					],
					[
						80423.0769230769,
						3,
						0
					],
					[
						80653.8461538461,
						3,
						0
					],
					[
						80769.2307692308,
						2,
						0
					],
					[
						80884.6153846153,
						3,
						0
					],
					[
						81115.3846153846,
						2,
						0
					],
					[
						80538.4615384615,
						1,
						0,
						"shoot"
					],
					[
						80538.4615384615,
						0,
						0,
						"shoot"
					],
					[
						81000,
						1,
						0,
						"shoot"
					],
					[
						81000,
						0,
						0,
						"shoot"
					]
				],
				"sectionBeats": 4,
				"altAnim": false,
				"gfSection": false,
				"bpm": 130,
				"changeBPM": false,
				"mustHitSection": true
			},
			{
				"typeOfSection": 0,
				"sectionNotes": [
					[
						81230.7692307692,
						3,
						0
					],
					[
						81346.1538461538,
						1,
						0
					],
					[
						81461.5384615385,
						3,
						0
					],
					[
						81576.9230769231,
						1,
						0
					],
					[
						81692.3076923077,
						3,
						0
					],
					[
						81807.6923076923,
						1,
						0
					],
					[
						81923.0769230769,
						3,
						0
					],
					[
						82038.4615384615,
						1,
						0
					],
					[
						81291.3461538461,
						2,
						0
					],
					[
						81519.2307692308,
						2,
						0
					],
					[
						81744.2307692308,
						2,
						0
					],
					[
						81980.7692307692,
						2,
						0
					],
					[
						81400.9615384615,
						0,
						0
					],
					[
						81628.8461538461,
						0,
						0
					],
					[
						81859.6153846154,
						0,
						0
					],
					[
						82087.5,
						0,
						0
					],
					[
						82153.8461538461,
						3,
						0
					],
					[
						82384.6153846154,
						1,
						0
					],
					[
						82846.1538461538,
						1,
						0
					],
					[
						82615.3846153846,
						3,
						0,
						"shoot"
					],
					[
						82615.3846153846,
						2,
						0,
						"shoot"
					],
					[
						82615.3846153846,
						1,
						0,
						"shoot"
					],
					[
						82615.3846153846,
						0,
						0,
						"shoot"
					]
				],
				"sectionBeats": 4,
				"altAnim": false,
				"gfSection": false,
				"bpm": 130,
				"changeBPM": false,
				"mustHitSection": true
			},
			{
				"typeOfSection": 0,
				"sectionNotes": [
					[
						83076.9230769231,
						3,
						0
					],
					[
						83192.3076923077,
						1,
						0
					],
					[
						83307.6923076923,
						3,
						0
					],
					[
						83423.0769230769,
						1,
						0
					],
					[
						83538.4615384615,
						3,
						0
					],
					[
						83653.8461538461,
						1,
						0
					],
					[
						83769.2307692308,
						3,
						0
					],
					[
						83884.6153846154,
						1,
						0
					],
					[
						83137.5,
						2,
						0
					],
					[
						83365.3846153846,
						2,
						0
					],
					[
						83590.3846153846,
						2,
						0
					],
					[
						83826.9230769231,
						2,
						0
					],
					[
						83247.1153846154,
						0,
						0
					],
					[
						83475,
						0,
						0
					],
					[
						83705.7692307692,
						0,
						0
					],
					[
						83933.6538461538,
						0,
						0
					],
					[
						84000,
						2,
						0
					],
					[
						84230.7692307692,
						0,
						0
					],
					[
						84692.3076923077,
						1,
						0
					],
					[
						84461.5384615384,
						2,
						0,
						"shoot"
					],
					[
						84461.5384615384,
						1,
						0,
						"shoot"
					],
					[
						84461.5384615384,
						0,
						0,
						"shoot"
					],
					[
						84461.5384615384,
						3,
						0,
						"shoot"
					]
				],
				"sectionBeats": 4,
				"altAnim": false,
				"gfSection": false,
				"bpm": 130,
				"changeBPM": false,
				"mustHitSection": true
			},
			{
				"typeOfSection": 0,
				"sectionNotes": [
					[
						84923.0769230769,
						3,
						0
					],
					[
						85153.8461538461,
						3,
						0
					],
					[
						85269.2307692307,
						1,
						0
					],
					[
						85384.6153846153,
						3,
						0
					],
					[
						85615.3846153846,
						3,
						0
					],
					[
						85730.7692307692,
						0,
						0
					],
					[
						85846.1538461538,
						2,
						0
					],
					[
						85961.5384615384,
						3,
						0
					],
					[
						86076.923076923,
						1,
						0
					],
					[
						86192.3076923076,
						0,
						0
					],
					[
						86307.6923076923,
						1,
						0
					],
					[
						86538.4615384615,
						3,
						0
					]
				],
				"sectionBeats": 4,
				"altAnim": false,
				"gfSection": false,
				"bpm": 130,
				"changeBPM": false,
				"mustHitSection": false
			},
			{
				"typeOfSection": 0,
				"sectionNotes": [
					[
						86769.2307692307,
						2,
						0
					],
					[
						87000,
						2,
						0
					],
					[
						87115.3846153846,
						0,
						0
					],
					[
						87230.7692307692,
						2,
						0
					],
					[
						87461.5384615384,
						2,
						0
					],
					[
						87576.923076923,
						3,
						0
					],
					[
						87692.3076923076,
						0,
						0
					],
					[
						87807.6923076923,
						1,
						0
					],
					[
						87923.0769230769,
						2,
						0
					],
					[
						88038.4615384615,
						3,
						0
					],
					[
						88153.8461538461,
						2,
						0
					],
					[
						88269.2307692307,
						1,
						0
					],
					[
						88500,
						0,
						0
					]
				],
				"sectionBeats": 4,
				"altAnim": false,
				"gfSection": false,
				"bpm": 130,
				"changeBPM": false,
				"mustHitSection": false
			},
			{
				"typeOfSection": 0,
				"sectionNotes": [
					[
						88615.3846153846,
						2,
						0
					],
					[
						88846.1538461538,
						2,
						0
					],
					[
						88961.5384615384,
						3,
						0
					],
					[
						89076.923076923,
						1,
						0
					],
					[
						89307.6923076923,
						1,
						0
					],
					[
						89423.0769230769,
						0,
						0
					],
					[
						89538.4615384615,
						3,
						0
					],
					[
						89653.8461538461,
						2,
						0
					],
					[
						89769.2307692307,
						0,
						0
					],
					[
						89884.6153846153,
						1,
						0
					],
					[
						90000,
						0,
						0
					],
					[
						90230.7692307692,
						3,
						0
					]
				],
				"sectionBeats": 4,
				"altAnim": false,
				"gfSection": false,
				"bpm": 130,
				"changeBPM": false,
				"mustHitSection": false
			},
			{
				"typeOfSection": 0,
				"sectionNotes": [
					[
						90461.5384615384,
						3,
						0
					],
					[
						90692.3076923076,
						1,
						0
					],
					[
						90807.6923076923,
						0,
						0
					],
					[
						91038.4615384615,
						0,
						0
					],
					[
						91153.8461538461,
						1,
						0
					],
					[
						91269.2307692307,
						3,
						0
					],
					[
						91384.6153846153,
						0,
						0
					],
					[
						91499.9999999999,
						1,
						0
					],
					[
						91615.3846153846,
						2,
						0
					],
					[
						91730.7692307692,
						3,
						0
					],
					[
						91846.1538461538,
						1,
						0
					],
					[
						91961.5384615384,
						2,
						0
					],
					[
						92076.923076923,
						3,
						0
					],
					[
						92192.3076923076,
						0,
						0
					]
				],
				"sectionBeats": 4,
				"altAnim": false,
				"gfSection": false,
				"bpm": 130,
				"changeBPM": false,
				"mustHitSection": false
			},
			{
				"typeOfSection": 0,
				"sectionNotes": [
					[
						92307.6923076923,
						7,
						0
					],
					[
						92538.4615384615,
						7,
						0
					],
					[
						92653.8461538461,
						5,
						0
					],
					[
						92769.2307692307,
						7,
						0
					],
					[
						93000,
						7,
						0
					],
					[
						93115.3846153846,
						4,
						0
					],
					[
						93230.7692307692,
						6,
						0
					],
					[
						93346.1538461538,
						7,
						0
					],
					[
						93461.5384615384,
						5,
						0
					],
					[
						93576.923076923,
						4,
						0
					],
					[
						93692.3076923077,
						5,
						0
					],
					[
						93923.0769230769,
						7,
						0
					],
					[
						92307.6923076923,
						3,
						0
					],
					[
						92538.4615384615,
						3,
						0
					],
					[
						92653.8461538461,
						1,
						0
					],
					[
						92769.2307692307,
						3,
						0
					],
					[
						93000,
						3,
						0
					],
					[
						93230.7692307692,
						2,
						0
					],
					[
						93346.1538461538,
						3,
						0
					],
					[
						93461.5384615384,
						1,
						0
					],
					[
						93576.923076923,
						0,
						0
					],
					[
						93692.3076923077,
						1,
						0
					],
					[
						93923.0769230769,
						3,
						0
					],
					[
						93115.3846153846,
						0,
						0,
						"shoot"
					],
					[
						93115.3846153846,
						1,
						0,
						"shoot"
					]
				],
				"sectionBeats": 4,
				"altAnim": false,
				"gfSection": false,
				"bpm": 130,
				"changeBPM": false,
				"mustHitSection": true
			},
			{
				"typeOfSection": 0,
				"sectionNotes": [
					[
						94153.8461538461,
						6,
						0
					],
					[
						94384.6153846153,
						6,
						0
					],
					[
						94500,
						4,
						0
					],
					[
						94615.3846153846,
						6,
						0
					],
					[
						94846.1538461538,
						6,
						0
					],
					[
						94961.5384615384,
						7,
						0
					],
					[
						95076.923076923,
						4,
						0
					],
					[
						95192.3076923076,
						5,
						0
					],
					[
						95307.6923076923,
						6,
						0
					],
					[
						95423.0769230769,
						7,
						0
					],
					[
						95538.4615384615,
						6,
						0
					],
					[
						94153.8461538461,
						2,
						0
					],
					[
						94384.6153846153,
						2,
						0
					],
					[
						94500,
						0,
						0
					],
					[
						94846.1538461538,
						2,
						0
					],
					[
						94961.5384615384,
						3,
						0
					],
					[
						95076.923076923,
						0,
						0
					],
					[
						95192.3076923076,
						1,
						0
					],
					[
						95307.6923076923,
						2,
						0
					],
					[
						95423.0769230769,
						3,
						0
					],
					[
						95538.4615384615,
						2,
						0
					],
					[
						95769.2307692307,
						4,
						0
					],
					[
						94615.3846153846,
						3,
						0,
						"shoot"
					],
					[
						94615.3846153846,
						2,
						0,
						"shoot"
					],
					[
						95769.2307692307,
						0,
						0,
						"shoot"
					],
					[
						95769.2307692307,
						1,
						0,
						"shoot"
					]
				],
				"sectionBeats": 4,
				"altAnim": false,
				"gfSection": false,
				"bpm": 130,
				"changeBPM": false,
				"mustHitSection": true
			},
			{
				"typeOfSection": 0,
				"sectionNotes": [
					[
						96000,
						6,
						0
					],
					[
						96230.7692307692,
						6,
						0
					],
					[
						96346.1538461538,
						7,
						0
					],
					[
						96461.5384615384,
						5,
						0
					],
					[
						96692.3076923076,
						5,
						0
					],
					[
						96807.6923076923,
						4,
						0
					],
					[
						96923.0769230769,
						7,
						0
					],
					[
						97038.4615384615,
						6,
						0
					],
					[
						97153.8461538461,
						4,
						0
					],
					[
						97269.2307692307,
						5,
						0
					],
					[
						97384.6153846153,
						4,
						0
					],
					[
						97615.3846153846,
						7,
						0
					],
					[
						96000,
						2,
						0
					],
					[
						96230.7692307692,
						2,
						0
					],
					[
						96346.1538461538,
						3,
						0
					],
					[
						96461.5384615384,
						1,
						0
					],
					[
						96807.6923076923,
						0,
						0
					],
					[
						96923.0769230769,
						3,
						0
					],
					[
						97038.4615384615,
						2,
						0
					],
					[
						97153.8461538461,
						0,
						0
					],
					[
						97269.2307692307,
						1,
						0
					],
					[
						97384.6153846153,
						0,
						0
					],
					[
						96692.3076923076,
						1,
						0,
						"shoot"
					],
					[
						96692.3076923076,
						2,
						0,
						"shoot"
					],
					[
						97615.3846153846,
						3,
						0,
						"shoot"
					],
					[
						97615.3846153846,
						2,
						0,
						"shoot"
					]
				],
				"sectionBeats": 4,
				"altAnim": false,
				"gfSection": false,
				"bpm": 130,
				"changeBPM": false,
				"mustHitSection": true
			},
			{
				"typeOfSection": 0,
				"sectionNotes": [
					[
						97846.1538461538,
						7,
						0
					],
					[
						98076.923076923,
						5,
						0
					],
					[
						98192.3076923076,
						4,
						0
					],
					[
						98423.0769230769,
						4,
						0
					],
					[
						98538.4615384615,
						5,
						0
					],
					[
						98653.8461538461,
						7,
						0
					],
					[
						98769.2307692307,
						4,
						0
					],
					[
						98884.6153846153,
						5,
						0
					],
					[
						99000,
						6,
						0
					],
					[
						99115.3846153846,
						7,
						0
					],
					[
						99230.7692307692,
						5,
						0
					],
					[
						99346.1538461538,
						6,
						0
					],
					[
						99461.5384615384,
						7,
						0
					],
					[
						99576.923076923,
						4,
						0
					],
					[
						97846.1538461538,
						3,
						0
					],
					[
						98076.923076923,
						1,
						0
					],
					[
						98192.3076923076,
						0,
						0
					],
					[
						98423.0769230769,
						0,
						0
					],
					[
						98653.8461538461,
						3,
						0
					],
					[
						98769.2307692307,
						0,
						0
					],
					[
						98884.6153846153,
						1,
						0
					],
					[
						99000,
						2,
						0
					],
					[
						99115.3846153846,
						3,
						0
					],
					[
						99230.7692307692,
						1,
						0
					],
					[
						99346.1538461538,
						2,
						0
					],
					[
						99461.5384615384,
						3,
						0
					],
					[
						99576.923076923,
						0,
						0
					],
					[
						98538.4615384615,
						1,
						0,
						"shoot"
					],
					[
						98538.4615384615,
						2,
						0,
						"shoot"
					]
				],
				"sectionBeats": 4,
				"altAnim": false,
				"gfSection": false,
				"bpm": 130,
				"changeBPM": false,
				"mustHitSection": true
			},
			{
				"typeOfSection": 0,
				"sectionNotes": [
					[
						99692.3076923076,
						3,
						0
					],
					[
						99807.6923076922,
						1,
						0
					],
					[
						99923.0769230769,
						0,
						0
					],
					[
						100038.461538461,
						3,
						0
					],
					[
						100153.846153846,
						2,
						0
					],
					[
						100269.230769231,
						1,
						0
					],
					[
						100384.615384615,
						0,
						0
					],
					[
						100615.384615385,
						3,
						0
					],
					[
						100730.769230769,
						1,
						0
					],
					[
						100846.153846154,
						0,
						0
					],
					[
						100961.538461538,
						3,
						0
					],
					[
						101076.923076923,
						2,
						0
					],
					[
						101192.307692308,
						1,
						0
					],
					[
						101307.692307692,
						0,
						0
					],
					[
						101423.076923077,
						2,
						0
					],
					[
						100500,
						1,
						0,
						"shoot"
					],
					[
						100500,
						2,
						0,
						"shoot"
					]
				],
				"sectionBeats": 4,
				"altAnim": false,
				"gfSection": false,
				"bpm": 130,
				"changeBPM": false,
				"mustHitSection": true
			},
			{
				"typeOfSection": 0,
				"sectionNotes": [
					[
						101538.461538461,
						3,
						0
					],
					[
						101653.846153846,
						0,
						0
					],
					[
						101769.230769231,
						1,
						0
					],
					[
						101884.615384615,
						3,
						0
					],
					[
						102000,
						0,
						0
					],
					[
						102115.384615385,
						2,
						0
					],
					[
						102230.769230769,
						3,
						0
					],
					[
						102346.153846154,
						2,
						0
					],
					[
						102461.538461538,
						1,
						0
					],
					[
						102576.923076923,
						3,
						0
					],
					[
						102692.307692308,
						0,
						0
					],
					[
						102807.692307692,
						3,
						0
					],
					[
						102923.076923077,
						1,
						0
					],
					[
						103038.461538461,
						2,
						0
					],
					[
						103153.846153846,
						3,
						0
					],
					[
						103269.230769231,
						2,
						0
					]
				],
				"sectionBeats": 4,
				"altAnim": false,
				"gfSection": false,
				"bpm": 130,
				"changeBPM": false,
				"mustHitSection": true
			},
			{
				"typeOfSection": 0,
				"sectionNotes": [
					[
						103384.615384615,
						2,
						0
					],
					[
						103500,
						3,
						0
					],
					[
						103615.384615385,
						0,
						0
					],
					[
						103730.769230769,
						1,
						0
					],
					[
						103846.153846154,
						2,
						0
					],
					[
						103961.538461538,
						3,
						0
					],
					[
						104076.923076923,
						0,
						0
					],
					[
						104192.307692308,
						1,
						0
					],
					[
						104307.692307692,
						3,
						0
					],
					[
						104423.076923077,
						1,
						0
					],
					[
						104653.846153846,
						0,
						0
					],
					[
						104769.230769231,
						3,
						0
					],
					[
						104884.615384615,
						1,
						0
					],
					[
						105000,
						2,
						0
					],
					[
						105115.384615385,
						3,
						0
					],
					[
						104538.461538461,
						2,
						0,
						"shoot"
					],
					[
						104538.461538461,
						3,
						0,
						"shoot"
					]
				],
				"sectionBeats": 4,
				"altAnim": false,
				"gfSection": false,
				"bpm": 130,
				"changeBPM": false,
				"mustHitSection": true
			},
			{
				"typeOfSection": 0,
				"sectionNotes": [
					[
						105230.769230769,
						3,
						0
					],
					[
						105346.153846154,
						1,
						0
					],
					[
						105461.538461538,
						0,
						0
					],
					[
						105576.923076923,
						3,
						0
					],
					[
						105692.307692308,
						2,
						0
					],
					[
						105807.692307692,
						1,
						0
					],
					[
						105923.076923077,
						0,
						0
					],
					[
						106038.461538461,
						2,
						0
					],
					[
						106153.846153846,
						3,
						0
					],
					[
						106384.615384615,
						0,
						0
					],
					[
						106500,
						3,
						0
					],
					[
						106615.384615385,
						2,
						0
					],
					[
						106730.769230769,
						1,
						0
					],
					[
						106846.153846154,
						0,
						0
					],
					[
						106961.538461538,
						2,
						0
					],
					[
						106269.230769231,
						1,
						0,
						"shoot"
					],
					[
						106269.230769231,
						2,
						0,
						"shoot"
					]
				],
				"sectionBeats": 4,
				"altAnim": false,
				"gfSection": false,
				"bpm": 130,
				"changeBPM": false,
				"mustHitSection": true
			},
			{
				"typeOfSection": 0,
				"sectionNotes": [
					[
						107076.923076923,
						7,
						0
					],
					[
						107192.307692308,
						5,
						0
					],
					[
						107307.692307692,
						4,
						0
					],
					[
						107423.076923077,
						7,
						0
					],
					[
						107538.461538461,
						6,
						0
					],
					[
						107653.846153846,
						5,
						0
					],
					[
						107769.230769231,
						4,
						0
					],
					[
						107884.615384615,
						6,
						0
					],
					[
						108000,
						7,
						0
					],
					[
						108115.384615385,
						5,
						0
					],
					[
						108230.769230769,
						4,
						0
					],
					[
						108346.153846154,
						7,
						0
					],
					[
						108461.538461538,
						6,
						0
					],
					[
						108576.923076923,
						5,
						0
					],
					[
						108692.307692308,
						4,
						0
					],
					[
						108807.692307692,
						6,
						0
					],
					[
						107076.923076923,
						3,
						0
					],
					[
						107192.307692308,
						1,
						0
					],
					[
						107307.692307692,
						0,
						0
					],
					[
						107423.076923077,
						3,
						0
					],
					[
						107538.461538461,
						2,
						0
					],
					[
						107653.846153846,
						1,
						0
					],
					[
						107769.230769231,
						0,
						0
					],
					[
						107884.615384615,
						2,
						0
					],
					[
						108000,
						3,
						0
					],
					[
						108115.384615385,
						1,
						0
					],
					[
						108230.769230769,
						0,
						0
					],
					[
						108346.153846154,
						3,
						0
					],
					[
						108461.538461538,
						2,
						0
					],
					[
						108576.923076923,
						1,
						0
					],
					[
						108692.307692308,
						0,
						0
					],
					[
						108807.692307692,
						2,
						0
					]
				],
				"sectionBeats": 4,
				"altAnim": false,
				"gfSection": false,
				"bpm": 130,
				"changeBPM": false,
				"mustHitSection": true
			},
			{
				"typeOfSection": 0,
				"sectionNotes": [
					[
						108923.076923077,
						7,
						0
					],
					[
						109038.461538461,
						4,
						0
					],
					[
						109153.846153846,
						5,
						0
					],
					[
						109269.230769231,
						7,
						0
					],
					[
						109384.615384615,
						4,
						0
					],
					[
						109500,
						6,
						0
					],
					[
						109615.384615385,
						7,
						0
					],
					[
						109730.769230769,
						6,
						0
					],
					[
						109846.153846154,
						5,
						0
					],
					[
						109961.538461538,
						7,
						0
					],
					[
						110076.923076923,
						4,
						0
					],
					[
						110192.307692308,
						7,
						0
					],
					[
						110307.692307692,
						5,
						0
					],
					[
						110423.076923077,
						6,
						0
					],
					[
						110538.461538461,
						7,
						0
					],
					[
						110653.846153846,
						6,
						0
					],
					[
						108923.076923077,
						3,
						0
					],
					[
						109038.461538461,
						0,
						0
					],
					[
						109153.846153846,
						1,
						0
					],
					[
						109269.230769231,
						3,
						0
					],
					[
						109384.615384615,
						0,
						0
					],
					[
						109500,
						2,
						0
					],
					[
						109615.384615385,
						3,
						0
					],
					[
						109730.769230769,
						2,
						0
					],
					[
						109846.153846154,
						1,
						0
					],
					[
						109961.538461538,
						3,
						0
					],
					[
						110076.923076923,
						0,
						0
					],
					[
						110192.307692308,
						3,
						0
					],
					[
						110307.692307692,
						1,
						0
					],
					[
						110423.076923077,
						2,
						0
					],
					[
						110538.461538461,
						3,
						0
					],
					[
						110653.846153846,
						2,
						0
					]
				],
				"sectionBeats": 4,
				"altAnim": false,
				"gfSection": false,
				"bpm": 130,
				"changeBPM": false,
				"mustHitSection": true
			},
			{
				"typeOfSection": 0,
				"sectionNotes": [
					[
						110769.230769231,
						6,
						0
					],
					[
						110884.615384615,
						7,
						0
					],
					[
						111000,
						4,
						0
					],
					[
						111115.384615385,
						5,
						0
					],
					[
						111230.769230769,
						6,
						0
					],
					[
						111346.153846154,
						7,
						0
					],
					[
						111461.538461538,
						4,
						0
					],
					[
						111576.923076923,
						5,
						0
					],
					[
						111692.307692308,
						7,
						0
					],
					[
						111807.692307692,
						5,
						0
					],
					[
						111923.076923077,
						6,
						0
					],
					[
						112038.461538461,
						4,
						0
					],
					[
						112153.846153846,
						7,
						0
					],
					[
						112269.230769231,
						5,
						0
					],
					[
						112384.615384615,
						6,
						0
					],
					[
						112500,
						7,
						0
					],
					[
						110769.230769231,
						2,
						0
					],
					[
						110884.615384615,
						3,
						0
					],
					[
						111000,
						0,
						0
					],
					[
						111115.384615385,
						1,
						0
					],
					[
						111230.769230769,
						2,
						0
					],
					[
						111346.153846154,
						3,
						0
					],
					[
						111461.538461538,
						0,
						0
					],
					[
						111576.923076923,
						1,
						0
					],
					[
						111692.307692308,
						3,
						0
					],
					[
						111807.692307692,
						1,
						0
					],
					[
						111923.076923077,
						2,
						0
					],
					[
						112038.461538461,
						0,
						0
					],
					[
						112153.846153846,
						3,
						0
					],
					[
						112269.230769231,
						1,
						0
					],
					[
						112384.615384615,
						2,
						0
					],
					[
						112500,
						3,
						0
					]
				],
				"sectionBeats": 4,
				"altAnim": false,
				"gfSection": false,
				"bpm": 130,
				"changeBPM": false,
				"mustHitSection": true
			},
			{
				"typeOfSection": 0,
				"sectionNotes": [
					[
						112615.384615385,
						7,
						0
					],
					[
						112730.769230769,
						5,
						0
					],
					[
						112846.153846154,
						4,
						0
					],
					[
						112961.538461538,
						7,
						0
					],
					[
						113076.923076923,
						6,
						0
					],
					[
						113192.307692308,
						5,
						0
					],
					[
						113307.692307692,
						4,
						0
					],
					[
						113423.076923077,
						6,
						0
					],
					[
						113538.461538461,
						7,
						0
					],
					[
						113653.846153846,
						5,
						0
					],
					[
						113769.230769231,
						4,
						0
					],
					[
						113884.615384615,
						7,
						0
					],
					[
						114000,
						6,
						0
					],
					[
						114115.384615385,
						5,
						0
					],
					[
						114230.769230769,
						4,
						0
					],
					[
						114346.153846154,
						6,
						0
					],
					[
						112615.384615385,
						3,
						0
					],
					[
						112730.769230769,
						1,
						0
					],
					[
						112846.153846154,
						0,
						0
					],
					[
						112961.538461538,
						3,
						0
					],
					[
						113076.923076923,
						2,
						0
					],
					[
						113192.307692308,
						1,
						0
					],
					[
						113307.692307692,
						0,
						0
					],
					[
						113423.076923077,
						2,
						0
					],
					[
						113538.461538461,
						3,
						0
					],
					[
						113653.846153846,
						1,
						0
					],
					[
						113769.230769231,
						0,
						0
					],
					[
						113884.615384615,
						3,
						0
					],
					[
						114000,
						2,
						0
					],
					[
						114115.384615385,
						1,
						0
					],
					[
						114230.769230769,
						0,
						0
					],
					[
						114346.153846154,
						2,
						0
					]
				],
				"sectionBeats": 4,
				"altAnim": false,
				"gfSection": false,
				"bpm": 130,
				"changeBPM": false,
				"mustHitSection": true
			},
			{
				"typeOfSection": 0,
				"sectionNotes": [
					[
						114461.538461538,
						7,
						0
					],
					[
						114692.307692308,
						7,
						0
					],
					[
						114807.692307692,
						5,
						0
					],
					[
						114923.076923077,
						7,
						0
					],
					[
						115153.846153846,
						7,
						0
					],
					[
						115269.230769231,
						4,
						0
					],
					[
						115384.615384615,
						6,
						0
					],
					[
						115500,
						7,
						0
					],
					[
						115615.384615385,
						5,
						0
					],
					[
						115730.769230769,
						4,
						0
					],
					[
						115846.153846154,
						5,
						0
					],
					[
						116076.923076923,
						7,
						0
					],
					[
						114461.538461538,
						3,
						0
					],
					[
						114692.307692308,
						3,
						0
					],
					[
						114807.692307692,
						1,
						0
					],
					[
						114923.076923077,
						3,
						0
					],
					[
						115153.846153846,
						3,
						0
					],
					[
						115269.230769231,
						0,
						0
					],
					[
						115384.615384615,
						2,
						0
					],
					[
						115500,
						3,
						0
					],
					[
						115615.384615385,
						1,
						0
					],
					[
						115730.769230769,
						0,
						0
					],
					[
						115846.153846154,
						1,
						0
					],
					[
						116076.923076923,
						3,
						0
					]
				],
				"sectionBeats": 4,
				"altAnim": false,
				"gfSection": false,
				"bpm": 130,
				"changeBPM": false,
				"mustHitSection": true
			},
			{
				"typeOfSection": 0,
				"sectionNotes": [
					[
						116307.692307692,
						6,
						0
					],
					[
						116538.461538462,
						6,
						0
					],
					[
						116653.846153846,
						4,
						0
					],
					[
						116769.230769231,
						6,
						0
					],
					[
						117000,
						6,
						0
					],
					[
						117115.384615385,
						7,
						0
					],
					[
						117230.769230769,
						4,
						0
					],
					[
						117346.153846154,
						5,
						0
					],
					[
						117461.538461538,
						6,
						0
					],
					[
						117576.923076923,
						7,
						0
					],
					[
						117692.307692308,
						6,
						0
					],
					[
						116307.692307692,
						2,
						0
					],
					[
						116538.461538462,
						2,
						0
					],
					[
						116653.846153846,
						0,
						0
					],
					[
						116769.230769231,
						2,
						0
					],
					[
						117000,
						2,
						0
					],
					[
						117115.384615385,
						3,
						0
					],
					[
						117230.769230769,
						0,
						0
					],
					[
						117346.153846154,
						1,
						0
					],
					[
						117461.538461538,
						2,
						0
					],
					[
						117576.923076923,
						3,
						0
					],
					[
						117692.307692308,
						2,
						0
					],
					[
						117923.076923077,
						4,
						0
					],
					[
						117923.076923077,
						0,
						0
					]
				],
				"sectionBeats": 4,
				"altAnim": false,
				"gfSection": false,
				"bpm": 130,
				"changeBPM": false,
				"mustHitSection": true
			},
			{
				"typeOfSection": 0,
				"sectionNotes": [
					[
						118153.846153846,
						6,
						0
					],
					[
						118384.615384615,
						6,
						0
					],
					[
						118500,
						7,
						0
					],
					[
						118615.384615385,
						5,
						0
					],
					[
						118846.153846154,
						5,
						0
					],
					[
						118961.538461538,
						4,
						0
					],
					[
						119076.923076923,
						7,
						0
					],
					[
						119192.307692308,
						6,
						0
					],
					[
						119307.692307692,
						4,
						0
					],
					[
						119423.076923077,
						5,
						0
					],
					[
						119538.461538462,
						4,
						0
					],
					[
						119769.230769231,
						7,
						0
					],
					[
						118153.846153846,
						2,
						0
					],
					[
						118384.615384615,
						2,
						0
					],
					[
						118500,
						3,
						0
					],
					[
						118615.384615385,
						1,
						0
					],
					[
						118846.153846154,
						1,
						0
					],
					[
						118961.538461538,
						0,
						0
					],
					[
						119076.923076923,
						3,
						0
					],
					[
						119192.307692308,
						2,
						0
					],
					[
						119307.692307692,
						0,
						0
					],
					[
						119423.076923077,
						1,
						0
					],
					[
						119538.461538462,
						0,
						0
					],
					[
						119769.230769231,
						3,
						0
					]
				],
				"sectionBeats": 4,
				"altAnim": false,
				"gfSection": false,
				"bpm": 130,
				"changeBPM": false,
				"mustHitSection": true
			},
			{
				"typeOfSection": 0,
				"sectionNotes": [
					[
						120000,
						7,
						0
					],
					[
						120230.769230769,
						5,
						0
					],
					[
						120346.153846154,
						4,
						0
					],
					[
						120576.923076923,
						4,
						0
					],
					[
						120692.307692308,
						5,
						0
					],
					[
						120807.692307692,
						7,
						0
					],
					[
						120923.076923077,
						4,
						0
					],
					[
						121038.461538461,
						5,
						0
					],
					[
						121153.846153846,
						6,
						0
					],
					[
						121269.230769231,
						7,
						0
					],
					[
						121384.615384615,
						5,
						0
					],
					[
						121500,
						6,
						0
					],
					[
						121615.384615385,
						7,
						0
					],
					[
						121730.769230769,
						4,
						0
					],
					[
						120000,
						3,
						0
					],
					[
						120230.769230769,
						1,
						0
					],
					[
						120346.153846154,
						0,
						0
					],
					[
						120576.923076923,
						0,
						0
					],
					[
						120692.307692308,
						1,
						0
					],
					[
						120807.692307692,
						3,
						0
					],
					[
						120923.076923077,
						0,
						0
					],
					[
						121038.461538461,
						1,
						0
					],
					[
						121153.846153846,
						2,
						0
					],
					[
						121269.230769231,
						3,
						0
					],
					[
						121384.615384615,
						1,
						0
					],
					[
						121500,
						2,
						0
					],
					[
						121615.384615385,
						3,
						0
					],
					[
						121730.769230769,
						0,
						0
					]
				],
				"sectionBeats": 4,
				"altAnim": false,
				"gfSection": false,
				"bpm": 130,
				"changeBPM": false,
				"mustHitSection": true
			},
			{
				"typeOfSection": 0,
				"sectionNotes": [
					[
						121846.153846154,
						7,
						0
					],
					[
						121961.538461538,
						5,
						0
					],
					[
						122076.923076923,
						4,
						0
					],
					[
						122192.307692308,
						7,
						0
					],
					[
						122307.692307692,
						6,
						0
					],
					[
						122423.076923077,
						5,
						0
					],
					[
						122538.461538461,
						4,
						0
					],
					[
						122653.846153846,
						6,
						0
					],
					[
						122769.230769231,
						7,
						0
					],
					[
						122884.615384615,
						5,
						0
					],
					[
						123000,
						4,
						0
					],
					[
						123115.384615385,
						7,
						0
					],
					[
						123230.769230769,
						6,
						0
					],
					[
						123346.153846154,
						5,
						0
					],
					[
						123461.538461538,
						4,
						0
					],
					[
						123576.923076923,
						6,
						0
					],
					[
						121846.153846154,
						3,
						0
					],
					[
						121961.538461538,
						1,
						0
					],
					[
						122076.923076923,
						0,
						0
					],
					[
						122192.307692308,
						3,
						0
					],
					[
						122307.692307692,
						2,
						0
					],
					[
						122423.076923077,
						1,
						0
					],
					[
						122538.461538461,
						0,
						0
					],
					[
						122653.846153846,
						2,
						0
					],
					[
						122769.230769231,
						3,
						0
					],
					[
						122884.615384615,
						1,
						0
					],
					[
						123000,
						0,
						0
					],
					[
						123115.384615385,
						3,
						0
					],
					[
						123230.769230769,
						2,
						0
					],
					[
						123346.153846154,
						1,
						0
					],
					[
						123461.538461538,
						0,
						0
					],
					[
						123576.923076923,
						2,
						0
					]
				],
				"sectionBeats": 4,
				"altAnim": false,
				"gfSection": false,
				"bpm": 130,
				"changeBPM": false,
				"mustHitSection": true
			},
			{
				"typeOfSection": 0,
				"sectionNotes": [
					[
						123692.307692308,
						7,
						0
					],
					[
						123807.692307692,
						4,
						0
					],
					[
						123923.076923077,
						5,
						0
					],
					[
						124038.461538461,
						7,
						0
					],
					[
						124153.846153846,
						4,
						0
					],
					[
						124269.230769231,
						6,
						0
					],
					[
						124384.615384615,
						7,
						0
					],
					[
						124500,
						6,
						0
					],
					[
						124615.384615385,
						5,
						0
					],
					[
						124730.769230769,
						7,
						0
					],
					[
						124846.153846154,
						4,
						0
					],
					[
						124961.538461538,
						7,
						0
					],
					[
						125076.923076923,
						5,
						0
					],
					[
						125192.307692308,
						6,
						0
					],
					[
						125307.692307692,
						7,
						0
					],
					[
						125423.076923077,
						6,
						0
					],
					[
						123692.307692308,
						3,
						0
					],
					[
						123807.692307692,
						0,
						0
					],
					[
						123923.076923077,
						1,
						0
					],
					[
						124038.461538461,
						3,
						0
					],
					[
						124153.846153846,
						0,
						0
					],
					[
						124269.230769231,
						2,
						0
					],
					[
						124384.615384615,
						3,
						0
					],
					[
						124500,
						2,
						0
					],
					[
						124615.384615385,
						1,
						0
					],
					[
						124730.769230769,
						3,
						0
					],
					[
						124846.153846154,
						0,
						0
					],
					[
						124961.538461538,
						3,
						0
					],
					[
						125076.923076923,
						1,
						0
					],
					[
						125192.307692308,
						2,
						0
					],
					[
						125307.692307692,
						3,
						0
					],
					[
						125423.076923077,
						2,
						0
					]
				],
				"sectionBeats": 4,
				"altAnim": false,
				"gfSection": false,
				"bpm": 130,
				"changeBPM": false,
				"mustHitSection": true
			},
			{
				"typeOfSection": 0,
				"sectionNotes": [
					[
						125538.461538461,
						6,
						0
					],
					[
						125653.846153846,
						7,
						0
					],
					[
						125769.230769231,
						4,
						0
					],
					[
						125884.615384615,
						5,
						0
					],
					[
						126000,
						6,
						0
					],
					[
						126115.384615385,
						7,
						0
					],
					[
						126230.769230769,
						4,
						0
					],
					[
						126346.153846154,
						5,
						0
					],
					[
						126461.538461538,
						7,
						0
					],
					[
						126576.923076923,
						5,
						0
					],
					[
						126692.307692308,
						6,
						0
					],
					[
						126807.692307692,
						4,
						0
					],
					[
						126923.076923077,
						7,
						0
					],
					[
						127038.461538461,
						5,
						0
					],
					[
						127153.846153846,
						6,
						0
					],
					[
						127269.230769231,
						7,
						0
					],
					[
						125538.461538461,
						2,
						0
					],
					[
						125653.846153846,
						3,
						0
					],
					[
						125769.230769231,
						0,
						0
					],
					[
						125884.615384615,
						1,
						0
					],
					[
						126000,
						2,
						0
					],
					[
						126115.384615385,
						3,
						0
					],
					[
						126230.769230769,
						0,
						0
					],
					[
						126346.153846154,
						1,
						0
					],
					[
						126461.538461538,
						3,
						0
					],
					[
						126576.923076923,
						1,
						0
					],
					[
						126692.307692308,
						2,
						0
					],
					[
						126807.692307692,
						0,
						0
					],
					[
						126923.076923077,
						3,
						0
					],
					[
						127038.461538461,
						1,
						0
					],
					[
						127153.846153846,
						2,
						0
					],
					[
						127269.230769231,
						3,
						0
					]
				],
				"sectionBeats": 4,
				"altAnim": false,
				"gfSection": false,
				"bpm": 130,
				"changeBPM": false,
				"mustHitSection": true
			},
			{
				"typeOfSection": 0,
				"sectionNotes": [
					[
						127384.615384615,
						7,
						0
					],
					[
						127500,
						5,
						0
					],
					[
						127615.384615385,
						4,
						0
					],
					[
						127730.769230769,
						7,
						0
					],
					[
						127846.153846154,
						6,
						0
					],
					[
						127961.538461538,
						5,
						0
					],
					[
						128076.923076923,
						4,
						0
					],
					[
						128192.307692308,
						6,
						0
					],
					[
						128307.692307692,
						7,
						0
					],
					[
						128423.076923077,
						5,
						0
					],
					[
						128538.461538461,
						4,
						0
					],
					[
						128653.846153846,
						7,
						0
					],
					[
						128769.230769231,
						6,
						0
					],
					[
						128884.615384615,
						5,
						0
					],
					[
						129000,
						4,
						0
					],
					[
						129115.384615385,
						6,
						0
					],
					[
						127384.615384615,
						3,
						0
					],
					[
						127500,
						1,
						0
					],
					[
						127615.384615385,
						0,
						0
					],
					[
						127730.769230769,
						3,
						0
					],
					[
						127846.153846154,
						2,
						0
					],
					[
						127961.538461538,
						1,
						0
					],
					[
						128076.923076923,
						0,
						0
					],
					[
						128192.307692308,
						2,
						0
					],
					[
						128307.692307692,
						3,
						0
					],
					[
						128423.076923077,
						1,
						0
					],
					[
						128538.461538461,
						0,
						0
					],
					[
						128653.846153846,
						3,
						0
					],
					[
						128769.230769231,
						2,
						0
					],
					[
						128884.615384615,
						1,
						0
					],
					[
						129000,
						0,
						0
					],
					[
						129115.384615385,
						2,
						0
					]
				],
				"sectionBeats": 4,
				"altAnim": false,
				"gfSection": false,
				"bpm": 130,
				"changeBPM": false,
				"mustHitSection": true
			},
			{
				"typeOfSection": 0,
				"sectionNotes": [
					[
						129230.769230769,
						3,
						807.692307692308
					]
				],
				"sectionBeats": 4,
				"altAnim": false,
				"gfSection": false,
				"bpm": 130,
				"changeBPM": false,
				"mustHitSection": true
			},
			{
				"sectionBeats": 4,
				"sectionNotes": [],
				"typeOfSection": 0,
				"gfSection": false,
				"altAnim": false,
				"mustHitSection": true,
				"changeBPM": false,
				"bpm": 130
			},
			{
				"typeOfSection": 0,
				"sectionNotes": [],
				"sectionBeats": 4,
				"altAnim": false,
				"gfSection": false,
				"bpm": 130,
				"changeBPM": false,
				"mustHitSection": true
			},
			{
				"typeOfSection": 0,
				"sectionNotes": [],
				"sectionBeats": 4,
				"altAnim": false,
				"gfSection": false,
				"bpm": 130,
				"changeBPM": false,
				"mustHitSection": true
			},
			{
				"sectionBeats": 4,
				"sectionNotes": [],
				"typeOfSection": 0,
				"gfSection": false,
				"altAnim": false,
				"mustHitSection": true,
				"changeBPM": false,
				"bpm": 130
			},
			{
				"sectionBeats": 4,
				"sectionNotes": [],
				"typeOfSection": 0,
				"gfSection": false,
				"altAnim": false,
				"mustHitSection": true,
				"changeBPM": false,
				"bpm": 130
			},
			{
				"sectionBeats": 4,
				"sectionNotes": [],
				"typeOfSection": 0,
				"gfSection": false,
				"altAnim": false,
				"mustHitSection": true,
				"changeBPM": false,
				"bpm": 130
			},
			{
				"typeOfSection": 0,
				"sectionNotes": [],
				"sectionBeats": 4,
				"altAnim": false,
				"gfSection": false,
				"bpm": 130,
				"changeBPM": false,
				"mustHitSection": true
			},
			{
				"typeOfSection": 0,
				"sectionNotes": [],
				"sectionBeats": 4,
				"altAnim": false,
				"gfSection": false,
				"bpm": 130,
				"changeBPM": false,
				"mustHitSection": true
			},
			{
				"typeOfSection": 0,
				"sectionNotes": [],
				"sectionBeats": 4,
				"altAnim": false,
				"gfSection": false,
				"bpm": 130,
				"changeBPM": false,
				"mustHitSection": true
			},
			{
				"typeOfSection": 0,
				"sectionNotes": [],
				"sectionBeats": 4,
				"altAnim": false,
				"gfSection": false,
				"bpm": 130,
				"changeBPM": false,
				"mustHitSection": true
			},
			{
				"typeOfSection": 0,
				"sectionNotes": [],
				"sectionBeats": 4,
				"altAnim": false,
				"gfSection": false,
				"bpm": 130,
				"changeBPM": false,
				"mustHitSection": true
			},
			{
				"sectionBeats": 4,
				"sectionNotes": [],
				"typeOfSection": 0,
				"gfSection": false,
				"altAnim": false,
				"mustHitSection": true,
				"changeBPM": false,
				"bpm": 130
			},
			{
				"gfSection": false,
				"altAnim": false,
				"typeOfSection": 0,
				"sectionNotes": [],
				"bpm": 130,
				"sectionBeats": 4,
				"changeBPM": false,
				"mustHitSection": true
			}
		],
		"events": [
			[
				49038.4615384615,
				[
					[
						"Change Character",
						"dad",
						"leafeon sleep"
					]
				]
			],
			[
				54461.5384615384,
				[
					[
						"Change Character",
						"dad",
						"angry"
					]
				]
			],
			[
				55384.6153846154,
				[
					[
						"Change Character",
						"dad",
						"angry leafeon"
					],
					[
						"Image Flash",
						"leafeon note sprite",
						"6"
					]
				]
			],
			[
				58153.8461538461,
				[
					[
						"leafeonEvent",
						"0.15",
						""
					]
				]
			],
			[
				67846.1538461538,
				[
					[
						"leafeonEvent",
						"0.15",
						""
					]
				]
			],
			[
				69692.3076923077,
				[
					[
						"leafeonEvent",
						"0.15",
						""
					]
				]
			],
			[
				82615.3846153846,
				[
					[
						"leafeonEvent",
						"0.15",
						""
					]
				]
			],
			[
				84461.5384615384,
				[
					[
						"leafeonEvent",
						"0.15",
						""
					]
				]
			],
			[
				84692.3076923076,
				[
					[
						"Image Flash",
						"black",
						"0.5"
					]
				]
			],
			[
				84923.0769230769,
				[
					[
						"Replace stage layer",
						"bg",
						"flower shop"
					],
					[
						"Change Character",
						"bf",
						"bf-eevee-run"
					],
					[
						"Change Character",
						"gf",
						"cantsee"
					]
				]
			]
		],
		"player2": "leafeon",
		"player3": null,
		"splashSkin": "noteSplashes",
		"song": "sleep sound",
		"needsVoices": true,
		"arrowSkin": "",
		"validScore": true,
		"stage": "flower shop",
		"bpm": 130,
		"speed": 2
	}
}